setup.py
aliyun/__init__.py
aliyun/log/__init__.py
aliyun/log/acl_config.py
aliyun/log/acl_response.py
aliyun/log/common_response.py
aliyun/log/consumer_group_request.py
aliyun/log/consumer_group_response.py
aliyun/log/cursor_response.py
aliyun/log/cursor_time_response.py
aliyun/log/external_store_config.py
aliyun/log/external_store_config_response.py
aliyun/log/getcontextlogsresponse.py
aliyun/log/gethistogramsrequest.py
aliyun/log/gethistogramsresponse.py
aliyun/log/getlogsrequest.py
aliyun/log/getlogsresponse.py
aliyun/log/histogram.py
aliyun/log/index_config.py
aliyun/log/index_config_response.py
aliyun/log/listlogstoresrequest.py
aliyun/log/listlogstoresresponse.py
aliyun/log/listtopicsrequest.py
aliyun/log/listtopicsresponse.py
aliyun/log/log_logs_pb2.py
aliyun/log/log_logs_raw_pb2.py
aliyun/log/logclient.py
aliyun/log/logclient_core.py
aliyun/log/logclient_operator.py
aliyun/log/logexception.py
aliyun/log/logger_hanlder.py
aliyun/log/logitem.py
aliyun/log/logrequest.py
aliyun/log/logresponse.py
aliyun/log/logstore_config_response.py
aliyun/log/logtail_config_detail.py
aliyun/log/logtail_config_response.py
aliyun/log/machine_group_detail.py
aliyun/log/machinegroup_response.py
aliyun/log/pluralize.py
aliyun/log/project_response.py
aliyun/log/pulllog_response.py
aliyun/log/putlogsrequest.py
aliyun/log/putlogsresponse.py
aliyun/log/queriedlog.py
aliyun/log/shard_response.py
aliyun/log/shipper_config.py
aliyun/log/shipper_response.py
aliyun/log/util.py
aliyun/log/version.py
aliyun/log/consumer/__init__.py
aliyun/log/consumer/checkpoint_tracker.py
aliyun/log/consumer/config.py
aliyun/log/consumer/consumer_client.py
aliyun/log/consumer/exceptions.py
aliyun/log/consumer/fetched_log_group.py
aliyun/log/consumer/heart_beat.py
aliyun/log/consumer/shard_worker.py
aliyun/log/consumer/tasks.py
aliyun/log/consumer/worker.py
aliyun/log/es_migration/__init__.py
aliyun/log/es_migration/collection_task.py
aliyun/log/es_migration/collection_task_config.py
aliyun_log_python_sdk_test.egg-info/PKG-INFO
aliyun_log_python_sdk_test.egg-info/SOURCES.txt
aliyun_log_python_sdk_test.egg-info/dependency_links.txt
aliyun_log_python_sdk_test.egg-info/requires.txt
aliyun_log_python_sdk_test.egg-info/top_level.txt